ciss_vae/__init__.py
ciss_vae/classes/__init__.py
ciss_vae/classes/cluster_dataset.py
ciss_vae/classes/vae.py
ciss_vae/data/__init__.py
ciss_vae/training/__init__.py
ciss_vae/training/autotune.py
ciss_vae/training/run_cissvae.py
ciss_vae/training/train_initial.py
ciss_vae/training/train_refit.py
ciss_vae/utils/__init__.py
ciss_vae/utils/clustering.py
ciss_vae/utils/helpers.py
ciss_vae/utils/loss.py
ciss_vae/utils/matrix.py
ciss_vae-1.0.3.dist-info/licenses/LICENSE
ciss_vae-1.0.3.dist-info/METADATA
ciss_vae-1.0.3.dist-info/WHEEL
ciss_vae-1.0.3.dist-info/top_level.txt
ciss_vae-1.0.3.dist-info/RECORD
