Metadata-Version: 2.4
Name: CISS-VAE
Version: 1.0.3
Summary: Clustering-Informed Shared-Structure Variational Autoencoder (CISS-VAE) for Missing Data Imputation
Author: Yasin Khadem Charvadeh, Kenneth Seier, Katherine S. Panageas, Danielle Vaithilingam, Mithat Gönen, Yuan Chen
License-Expression: MIT
Project-URL: Homepage, https://ciss-vae.readthedocs.io/en/latest/index.html
Project-URL: Documentation, https://ciss-vae.readthedocs.io/en/latest/vignette.html
Project-URL: Source, https://github.com/CISS-VAE/CISS-VAE-python
Project-URL: Publication, https://doi.org/10.1002/sim.70335
Keywords: cissvae,ciss-vae,ciss_vae,imputation,VAE,missingness,missing data
Requires-Python: >=3.10
License-File: LICENSE
Requires-Dist: numpy>=1.22
Requires-Dist: pandas>=2.0
Requires-Dist: torch>=2.0
Requires-Dist: optuna>=4.3
Requires-Dist: rich
Requires-Dist: typing
Requires-Dist: matplotlib
Requires-Dist: scikit-learn
Requires-Dist: leidenalg
Requires-Dist: python-igraph
Provides-Extra: dev
Requires-Dist: mypy; extra == "dev"
Requires-Dist: pytest>=7.0.0; extra == "dev"
Requires-Dist: pytest-cov>=4.0.0; extra == "dev"
Requires-Dist: pytest-mock>=3.10.0; extra == "dev"
Requires-Dist: black>=22.0.0; extra == "dev"
Requires-Dist: flake8>=5.0.0; extra == "dev"
Requires-Dist: pre-commit>=2.20.0; extra == "dev"
Provides-Extra: docs
Requires-Dist: sphinx; extra == "docs"
Requires-Dist: sphinx_rtd_theme; extra == "docs"
Requires-Dist: myst-parser; extra == "docs"
Dynamic: license-file
